ti_python/__init__.py
ti_python/__main__.py
ti_python/compiler.py
ti_python/generate.py
ti_python/tokenizer.py
ti_python/types.py
ti_python-0.1.2.dist-info/LICENSE
ti_python-0.1.2.dist-info/METADATA
ti_python-0.1.2.dist-info/WHEEL
ti_python-0.1.2.dist-info/entry_points.txt
ti_python-0.1.2.dist-info/top_level.txt
ti_python-0.1.2.dist-info/RECORD
