Metadata-Version: 2.2
Name: ti-python
Version: 0.1.2
Summary: A versatile compiler to make TI-BASIC programs with Python 3 syntax
Author: simplyrohan
License: GPL-3.0-or-later
Project-URL: Homepage, https://github.com/simplyrohan/ti-python
Project-URL: Repository, https://github.com/simplyrohan/ti-python
Requires-Python: >=3.9
License-File: LICENSE
